sequence_layers/__init__.py
sequence_layers/internal/types.py
sequence_layers/jax/__init__.py
sequence_layers/jax/attention.py
sequence_layers/jax/combinators.py
sequence_layers/jax/conditioning.py
sequence_layers/jax/convolution.py
sequence_layers/jax/dense.py
sequence_layers/jax/dsp.py
sequence_layers/jax/export.py
sequence_layers/jax/meta.py
sequence_layers/jax/normalization.py
sequence_layers/jax/pooling.py
sequence_layers/jax/position.py
sequence_layers/jax/recurrent.py
sequence_layers/jax/sharding.py
sequence_layers/jax/signal.py
sequence_layers/jax/simple.py
sequence_layers/jax/test_utils.py
sequence_layers/jax/time_varying.py
sequence_layers/jax/types.py
sequence_layers/jax/typing.py
sequence_layers/jax/utils.py
sequence_layers/jax/examples/gemma3n_audio_encoder.py
sequence_layers/tensorflow/__init__.py
sequence_layers/tensorflow/attention.py
sequence_layers/tensorflow/combinators.py
sequence_layers/tensorflow/conditioning.py
sequence_layers/tensorflow/convolution.py
sequence_layers/tensorflow/dense.py
sequence_layers/tensorflow/dsp.py
sequence_layers/tensorflow/normalization.py
sequence_layers/tensorflow/pooling.py
sequence_layers/tensorflow/position.py
sequence_layers/tensorflow/recurrent.py
sequence_layers/tensorflow/simple.py
sequence_layers/tensorflow/squeeze.py
sequence_layers/tensorflow/test_util.py
sequence_layers/tensorflow/time_varying.py
sequence_layers/tensorflow/types.py
sequence_layers/tensorflow/utils.py
sequence_layers/tensorflow/examples/bert.py
sequence_layers/tensorflow/examples/conformer.py
sequence_layers/tensorflow/examples/deep_voice.py
sequence_layers/tensorflow/examples/listen_attend_spell.py
sequence_layers/tensorflow/examples/mobilenet.py
sequence_layers/tensorflow/examples/t5.py
sequence_layers/tensorflow/examples/tacotron.py
sequence_layers/tensorflow/examples/transformer.py
sequence_layers/tensorflow/examples/very_attentive_tacotron.py
sequence_layers/tensorflow/examples/wavernn.py
sequence_layers-0.1.dist-info/licenses/LICENSE
sequence_layers-0.1.dist-info/WHEEL
sequence_layers-0.1.dist-info/METADATA
sequence_layers-0.1.dist-info/RECORD
