Metadata-Version: 2.4
Name: sequence_layers
Version: 0.1
Summary: Sequence Layers neural network layer library from Google.
Keywords: 
Author-email: RJ Skerry-Ryan <rjryan@google.com>
Requires-Python: >=3.11
Classifier: License :: OSI Approved :: Apache Software License
Classifier: Intended Audience :: Science/Research
License-File: LICENSE
Requires-Dist: einops
Requires-Dist: flax
Requires-Dist: jax
Requires-Dist: jaxtyping
Requires-Dist: numpy
Requires-Dist: orbax-export
Requires-Dist: recurrentgemma[jax]
Requires-Dist: typeguard==2.13.3
Requires-Dist: absl-py ; extra == "dev"
Requires-Dist: chex ; extra == "dev"
Requires-Dist: orbax ; extra == "dev"
Requires-Dist: pytest ; extra == "dev"
Requires-Dist: pytest-xdist ; extra == "dev"
Requires-Dist: pylint>=2.6.0 ; extra == "dev"
Requires-Dist: pyink ; extra == "dev"
Requires-Dist: tensorflow ; extra == "dev"
Requires-Dist: attrs ; extra == "tensorflow"
Requires-Dist: scipy ; extra == "tensorflow"
Requires-Dist: tensorflow ; extra == "tensorflow"
Requires-Dist: tf_keras ; extra == "tensorflow"
Project-URL: repository, https://github.com/google/sequence-layers
Provides-Extra: dev
Provides-Extra: tensorflow
